italian_dictionary/__init__.py
italian_dictionary/dictionary.py
italian_dictionary/exceptions.py
italian_dictionary/scraper.py
italian_dictionary-1.1.1.dist-info/METADATA
italian_dictionary-1.1.1.dist-info/RECORD
italian_dictionary-1.1.1.dist-info/WHEEL
italian_dictionary-1.1.1.dist-info/top_level.txt
