Metadata-Version: 2.1
Name: italian-dictionary
Version: 1.1.1
Summary: A package which retrieves meaning and other informations about italian words.
Home-page: https://github.com/sphoneix22/italian_dictionary
Author: sphoneix
Author-email: simone.pugliese21@gmail.com
License: UNKNOWN
Platform: UNKNOWN
Classifier: Programming Language :: Python :: 3
Classifier: License :: OSI Approved :: MIT License
Classifier: Operating System :: OS Independent
